SoL.egg-info/PKG-INFO
SoL.egg-info/SOURCES.txt
SoL.egg-info/dependency_links.txt
SoL.egg-info/entry_points.txt
SoL.egg-info/not-zip-safe
SoL.egg-info/requires.txt
SoL.egg-info/top_level.txt
alembic/env.py
alembic/versions/1e49ee0210d7_add_breaker_column_to_matches.py
alembic/versions/24b38e397148_add_a_nationalliable_column_to_users.py
alembic/versions/36fa49561cd2_allow_more_than_one_tourney_per_day.py
alembic/versions/448c00f2ec1e_add_a_relative_position_to_competitors.py
alembic/versions/4792dcb3da70_make_delaycompatriotpairing_an_int_.py
alembic/versions/8dda46f71ced_handle_best_of_three_matches.py
alembic/versions/918717a067a6_add_an_optional_social_site_url_to_.py
alembic/versions/a67281b72424_add_max_rating_level_to_users.py
alembic/versions/aa0288cff765_make_players_and_clubs_nationality_.py
alembic/versions/d311277a4da7_widen_urls_size_to_128_characters.py
alembic/versions/ddd5d82c8e56_store_per_board_misses_values_not_just_.py
alembic/versions/e4348b488298_add_a_system_column_to_tourneys_to_.py
alembic/versions/ffec21d0a5a0_add_boards_table.py
sol-5.14.dist-info/METADATA
sol-5.14.dist-info/WHEEL
sol-5.14.dist-info/entry_points.txt
sol/__init__.py
sol/i18n.py
sol/locale/en/LC_MESSAGES/sol-client.mo
sol/locale/en/LC_MESSAGES/sol-server.mo
sol/locale/en_GB/LC_MESSAGES/sol-client.mo
sol/locale/en_GB/LC_MESSAGES/sol-client.po
sol/locale/en_GB/LC_MESSAGES/sol-server.mo
sol/locale/en_GB/LC_MESSAGES/sol-server.po
sol/locale/en_US/LC_MESSAGES/sol-client.mo
sol/locale/en_US/LC_MESSAGES/sol-client.po
sol/locale/en_US/LC_MESSAGES/sol-server.mo
sol/locale/en_US/LC_MESSAGES/sol-server.po
sol/locale/fr/LC_MESSAGES/sol-client.mo
sol/locale/fr/LC_MESSAGES/sol-client.po
sol/locale/fr/LC_MESSAGES/sol-server.mo
sol/locale/fr/LC_MESSAGES/sol-server.po
sol/locale/it/LC_MESSAGES/sol-client.mo
sol/locale/it/LC_MESSAGES/sol-client.po
sol/locale/it/LC_MESSAGES/sol-server.mo
sol/locale/it/LC_MESSAGES/sol-server.po
sol/locale/ja/LC_MESSAGES/sol-client.mo
sol/locale/ja/LC_MESSAGES/sol-server.mo
sol/locale/nb_NO/LC_MESSAGES/sol-client.mo
sol/locale/nb_NO/LC_MESSAGES/sol-server.mo
sol/locale/nl/LC_MESSAGES/sol-client.mo
sol/locale/pl/LC_MESSAGES/sol-client.mo
sol/locale/ru/LC_MESSAGES/sol-client.mo
sol/locale/ru/LC_MESSAGES/sol-server.mo
sol-5.14.dist-info/RECORD
