Metadata-Version: 2.1
Name: SoL
Version: 5.14
Summary: Carrom tournaments management
Keywords: web,wsgi,pyramid,carrom,tournaments,swiss system,knockout system,round-robin system
Author-Email: Lele Gaifax <lele@metapensiero.it>
License: GPLv3+
Classifier: Development Status :: 5 - Production/Stable
Classifier: Programming Language :: Python
Classifier: Programming Language :: Python :: 3
Classifier: Programming Language :: Python :: 3 :: Only
Classifier: Programming Language :: Python :: 3.10
Classifier: Programming Language :: Python :: 3.11
Classifier: Programming Language :: Python :: 3.12
Classifier: Programming Language :: JavaScript
Classifier: Operating System :: OS Independent
Classifier: Framework :: Pyramid
Classifier: Intended Audience :: End Users/Desktop
Classifier: License :: OSI Approved :: GNU General Public License v3 or later (GPLv3+)
Classifier: Natural Language :: English
Classifier: Natural Language :: Italian
Classifier: Topic :: Games/Entertainment
Classifier: Topic :: Internet :: WWW/HTTP
Classifier: Topic :: Internet :: WWW/HTTP :: WSGI :: Application
Classifier: Development Status :: 5 - Production/Stable
Project-URL: Homepage, https://sol5.metapensiero.it
Project-URL: Repository, https://gitlab.com/metapensiero/SoL
Requires-Python: >=3.10
Requires-Dist: alembic
Requires-Dist: babel
Requires-Dist: itsdangerous
Requires-Dist: mako
Requires-Dist: markupsafe
Requires-Dist: metapensiero.extjs.desktop
Requires-Dist: metapensiero.sqlalchemy.proxy
Requires-Dist: pycountry
Requires-Dist: pynacl
Requires-Dist: pyramid
Requires-Dist: pyramid-mailer
Requires-Dist: pyramid-mako
Requires-Dist: pyramid-tm
Requires-Dist: python-rapidjson
Requires-Dist: reportlab
Requires-Dist: repoze.sendmail
Requires-Dist: ruamel.yaml
Requires-Dist: ruamel.yaml.clib
Requires-Dist: sqlalchemy
Requires-Dist: transaction
Requires-Dist: translationstring
Requires-Dist: waitress
Requires-Dist: xlsxwriter
Requires-Dist: zope.sqlalchemy
Provides-Extra: test
Requires-Dist: coverage; extra == "test"
Requires-Dist: metapensiero.sqlalchemy.dbloady; extra == "test"
Requires-Dist: pytest; extra == "test"
Requires-Dist: pytest-cov; extra == "test"
Requires-Dist: webtest; extra == "test"
Provides-Extra: dev
Requires-Dist: build; extra == "dev"
Requires-Dist: bump-my-version; extra == "dev"
Requires-Dist: calmjs.parse; extra == "dev"
Requires-Dist: hupper; extra == "dev"
Requires-Dist: pygments; extra == "dev"
Requires-Dist: requests; extra == "dev"
Requires-Dist: rjsmin; extra == "dev"
Requires-Dist: secretstorage; extra == "dev"
Requires-Dist: sphinx; extra == "dev"
Requires-Dist: twine; extra == "dev"
